{
  "solargraph.useBundler": true,
  "cSpell.userWords": [
    "APII",
    "APIV",
    "Akbari",
    "Amazings",
    "Amirhossein",
    "Ariana",
    "Authed",
    "Classname",
    "Cyclomatic",
    "DATETIME",
    "DETIALED",
    "Descriptional",
    "Figma",
    "Fira",
    "Formik",
    "Geometria",
    "Gomanic",
    "Irancell",
    "JALALI",
    "Kamya",
    "Kryo",
    "Leaderf",
    "Neue",
    "Noto",
    "PDFSVG",
    "Parens",
    "Plug'n'Play",
    "Progressbar",
    "QRSVG",
    "Roboto",
    "Segoe",
    "Semibold",
    "Seperator",
    "Storyshots",
    "TODOs",
    "Timeago",
    "Toastr",
    "Toman",
    "Unmount",
    "VIEWPORTS",
    "ZIPSVG",
    "amirhosseinak",
    "averta",
    "between",
    "bluh",
    "bolditalic",
    "browserslist",
    "cacheable",
    "calc",
    "center",
    "column",
    "commitlint",
    "commitlintrc",
    "craco",
    "davys",
    "digiclub",
    "digikala",
    "digistyle",
    "dispalyed",
    "docgen",
    "echarts",
    "extend",
    "fidibo",
    "flex",
    "flexbox",
    "flexbugs",
    "flowtype",
    "fontawesome",
    "fontiran",
    "freshbasket",
    "full",
    "funcobj",
    "gutentags",
    "iapp",
    "icare",
    "iconly",
    "ifood",
    "ipark",
    "issuetype",
    "jalaali",
    "jsdoc",
    "jspa",
    "lightitalic",
    "linkedin",
    "lintstagedrc",
    "localforage",
    "mapbox",
    "markdownlint",
    "mediumitalic",
    "mtnirancell",
    "muirtl",
    "mygroup",
    "nextjs",
    "nocheck",
    "nums",
    "opentype",
    "persistor",
    "phanous",
    "precaching",
    "preconnect",
    "preload",
    "prettierrc",
    "qrcode",
    "reduxjs",
    "relative",
    "serializers",
    "solargraph",
    "spacing",
    "stretch",
    "stylelint",
    "stylelintrc",
    "stylis",
    "tailwindcss",
    "toastify",
    "truetype",
    "uuidv",
    "vhand",
    "whatsapp",
    "whatsup",
    "yarnrc",
    "آبان",
    "اعلام",
    "امتیاز",
    "امیرحسین",
    "اکبری",
    "باقی",
    "برند",
    "بپرسید",
    "توسط",
    "دریافت",
    "رایگان",
    "سایر",
    "غیراصل",
    "لاتین",
    "نمایید",
    "گیرنده"
  ],
  "coc.preferences.formatOnSaveFiletypes": [
    "javascriptreact",
    "jsonc",
    "json",
    "javascript",
    "markdown",
    "css",
    "scss",
    "html",
    "yaml",
    "typescript",
    "typescriptreact"
  ],
  "javascript.suggest.autoImports": true,
  "cSpellExt.enableDictionaries": ["persian"],
  "cSpell.language": "en,fa"
}
